python_todotxt-0.1.1.dist-info/DESCRIPTION.rst
python_todotxt-0.1.1.dist-info/METADATA
python_todotxt-0.1.1.dist-info/RECORD
python_todotxt-0.1.1.dist-info/WHEEL
python_todotxt-0.1.1.dist-info/metadata.json
python_todotxt-0.1.1.dist-info/top_level.txt
tests/__init__.py
tests/compare_mock_test.py
tests/entry_tests/__init__.py
tests/entry_tests/merge_test.py
tests/entry_tests/modify_test.py
tests/entry_tests/parse_test.py
tests/entry_tests/setter_test.py
tests/entry_tests/test_data.py
tests/entry_tests/util_test.py
todotxt/__init__.py
todotxt/entry.py
todotxt/file.py
todotxt/utils.py
