Metadata-Version: 2.0
Name: python-todotxt
Version: 0.1.1
Summary: Simple python library for todo.txt file format
Home-page: https://gitlab.com/SirEdvin/python-todotxt
Author: Bogdan Gladyshev
Author-email: siredvin.dark@gmail.com
License: MIT license
Keywords: todo.txt
Platform: UNKNOWN
Classifier: Development Status :: 5 - Production/Stable
Classifier: Intended Audience :: Developers
Classifier: License :: OSI Approved :: MIT License
Classifier: Natural Language :: English
Classifier: Programming Language :: Python :: 3.6
